hcli_hai/__init__.py
hcli_hai/__main__.py
hcli_hai/config.py
hcli_hai/hutils.py
hcli_hai/package.py
hcli_hai/cli/__init__.py
hcli_hai/cli/cli.py
hcli_hai/cli/config.py
hcli_hai/cli/jobqueue.py
hcli_hai/cli/logger.py
hcli_hai/cli/runner.py
hcli_hai/cli/service.py
hcli_hai/cli/template.json
hcli_hai/cli/ai/ai.py
hcli_hai/cli/ai/behavior.py
hcli_hai/cli/ai/context.py
hcli_hai/cli/ai/model.py
hcli_hai/cli/utils/formatting.py
hcli_hai/cli/utils/hutils.py
hcli_hai/cli/utils/summary.py
hcli_hai/data/hcli_hai.1
hcli_hai-3.4.2.dist-info/licenses/LICENSE.txt
hcli_hai-3.4.2.dist-info/METADATA
hcli_hai-3.4.2.dist-info/WHEEL
hcli_hai-3.4.2.dist-info/entry_points.txt
hcli_hai-3.4.2.dist-info/top_level.txt
hcli_hai-3.4.2.dist-info/RECORD
