Metadata-Version: 2.4
Name: hcli_hai
Version: 3.4.2
Summary: HCLI hai is a python package wrapper that contains an HCLI sample application (hai); hai is an HCLI for interacting with Anthropic's Claude or OpenAI's GPT AI models via terminal input and output streams.
Author-email: Jeff Michaud <cometaj2@proton.me>
License: MIT
Project-URL: Homepage, https://github.com/cometaj2/hcli_hai
Keywords: ai,llm,cli,client,server,connector,hypermedia,rest,generic,development
Classifier: Development Status :: 4 - Beta
Classifier: Intended Audience :: Developers
Classifier: Topic :: Software Development
Classifier: Programming Language :: Python :: 3.10
Classifier: Programming Language :: Python :: 3.11
Classifier: Programming Language :: Python :: 3.12
License-File: LICENSE.txt
Requires-Dist: tiktoken==0.9.0
Requires-Dist: anthropic==0.49.0
Requires-Dist: huckle<6.0.0,>=5.7.0
Requires-Dist: apscheduler==3.11.0
Requires-Dist: hcli-problem-details==0.1.1
Dynamic: license-file
